{
  "id": "31c27b4f-2ebe-4dbd-ae7d-8193ab55fc14",
  "sessionId": "s_njlk7hja5y9",
  "timestamp": "2025-08-16T06:29:51.275Z",
  "source": "diary",
  "topic": "Case studies of brands balancing trend alignment with authenticity",
  "content": "Generated from lens processing: My working hypothesis is that by focusing on the brand's core mission and timeless values such as authenticity, resilience, and innovation, we can create a story hook that resonates across diverse demographics. My next step is to research successful case studies of brands that have effectively leveraged these values in their storytelling. Additionally, I will explore psychological studies on emotional resonance to refine our approach, ensuring that the content not only aligns with the brand's identity but also emotionally engages the audience.",
  "tags": [
    "autopoietic",
    "lens-generated"
  ],
  "derivedTasks": [],
  "metadata": {
    "lensSessionId": "f64e24ce-8bc6-4312-b9bb-2655b40a8aaf",
    "trigger": "If I wanted to make marketing content today, what story hook would I use?",
    "generationTimestamp": "2025-08-16T06:29:51.275Z"
  },
  "createdAt": "2025-08-16T06:29:51.275Z",
  "updatedAt": "2025-08-16T06:29:51.275Z"
}