{
  "id": "366de921-30d2-4e16-84bc-06c57981a0c3",
  "sessionId": "s_njlk7hja5y9",
  "timestamp": "2025-08-16T08:33:30.282Z",
  "source": "research",
  "topic": "Research: AI integration impact on energy policy changes",
  "content": "**Research Summary: AI Integration Impact on Energy Policy Changes**\n\n**1. Key Findings or Insights:**\n\nThe integration of Artificial Intelligence (AI) into energy policy and management has demonstrated transformative potential across various dimensions. AI technologies enhance energy efficiency by optimizing grid management, predicting energy demand, and facilitating the integration of renewable sources like solar and wind. AI-driven predictive analytics allow for more accurate forecasting of energy production and consumption patterns, which helps in minimizing waste and improving the reliability of energy supply. Additionally, AI can significantly contribute to reducing carbon emissions by optimizing the deployment and operation of renewable energy assets, thus supporting sustainable energy policies.\n\n**2. Market Relevance:**\n\nIn the context of the solar and broader renewable energy sectors, the relevance of AI integration is profound. The global push towards renewable energy sources is heavily supported by AI technologies that enhance grid stability and facilitate higher penetration of intermittent renewable sources. For solar energy, AI can predict solar insolation and optimize panel alignment and maintenance schedules, increasing efficiency and reducing operational costs. Energy companies are increasingly adopting AI to stay competitive, making it a critical component of strategic planning and policy development in the energy sector. As AI continues to evolve, its role in shaping energy markets and policies will likely expand, influencing regulatory frameworks and investment flows.\n\n**3. Actionable Implications:**\n\n- Policymakers should prioritize the development of AI-friendly regulatory environments that encourage innovation and investment in AI technologies for the energy sector.\n- Energy companies should invest in AI capabilities to enhance operational efficiencies and align with emerging policy directions focused on sustainability and carbon reduction.\n- Collaborative efforts between AI developers, energy providers, and policymakers are essential to address challenges such as data sharing, privacy, and the ethical use of AI technologies.\n\n**4. Questions for Further Investigation:**\n\n- How can AI integration be balanced with concerns regarding data privacy and security in the energy sector?\n- What are the long-term economic impacts of AI-driven energy policy changes on traditional energy sectors, such as fossil fuels?\n- How can AI be leveraged to enhance the resilience of energy infrastructure against climate change-induced disruptions?\n- What role can AI play in the equitable distribution of energy resources globally, and how can policies be crafted to support this?\n\nThis summary provides a snapshot of the significant impact AI has on energy policy, underscoring its market relevance and the need for strategic actions to harness its full potential. Further investigation into these areas can help drive effective integration and address the challenges associated with AI in energy policy.",
  "tags": [
    "research",
    "autopoietic"
  ],
  "derivedTasks": [],
  "metadata": {
    "researchQuery": "AI integration impact on energy policy changes",
    "conductedAt": "2025-08-16T08:33:30.282Z",
    "method": "ai-analysis"
  },
  "createdAt": "2025-08-16T08:33:30.282Z",
  "updatedAt": "2025-08-16T08:33:30.282Z"
}