{
  "id": "3a583c32-6e8f-4bbe-82c1-fac285d40622",
  "sessionId": "s_njlk7hja5y9",
  "timestamp": "2025-08-19T06:49:41.755Z",
  "source": "research",
  "topic": "Research: emerging industry trends benefiting from simulation",
  "content": "**Research Summary: Emerging Industry Trends Benefiting from Simulation**\n\n1. **Key Findings or Insights:**\n   Simulation technologies are becoming increasingly pivotal across various industries, with significant advancements noted in the solar, artificial intelligence (AI), and energy sectors. These technologies enable the modeling and analysis of complex systems, improving efficiency, reducing costs, and enhancing innovation. In the solar industry, simulation tools are used to optimize photovoltaic system designs and predict energy generation under different conditions, thus improving yield and reliability. In AI, simulations help in training algorithms by providing vast amounts of synthetic data, accelerating machine learning processes, and enhancing decision-making capabilities. In the energy sector, simulations assist in grid management, optimizing energy storage solutions, and integrating renewable energy sources more effectively.\n\n2. **Market Relevance:**\nThe application of simulation in these sectors is highly relevant as companies strive to innovate and remain competitive. For the solar industry, simulation enhances the accuracy of solar farm outputs and aids in strategic planning for deployment, crucial in meeting the rising demand for renewable energy. In AI, simulation is essential for developing robust AI models that can operate in real-world conditions, thereby broadening the scope of AI applications and speeding up the time to market for AI-driven solutions. In the broader energy sector, simulation supports the transition to sustainable energy systems by enabling better design and management of energy networks, reducing risks, and improving operational efficiencies.\n\n3. **Actionable Implications:**\nBusinesses should invest in advanced simulation tools to gain insights into system behaviors and optimize operations. For solar companies, adopting simulation technologies can enhance design precision and operational efficiency, leading to reduced costs and increased energy output. AI firms should leverage simulation to improve algorithm training and testing, thereby accelerating development cycles and innovation. Energy companies can use simulation to optimize grid management and energy storage, ensuring more reliable and efficient integration of renewable energy sources.\n\n4. **Questions for Further Investigation:**\n- How can simulation technologies be further integrated with real-time data analytics to enhance predictive accuracy in these sectors?\n- What are the cost-benefit ratios of implementing advanced simulation tools for small to medium enterprises in the solar and energy sectors?\n- How can the scalability of simulation technologies be improved to accommodate the growing complexity of systems in AI and energy?\n- What are the potential cybersecurity risks associated with the increased reliance on simulation technologies, and how can they be mitigated?\n\nThis research underscores the transformative potential of simulation technologies in driving industry innovation and efficiency, highlighting the need for continuous exploration and adoption of these tools.",
  "tags": [
    "research",
    "autopoietic"
  ],
  "derivedTasks": [],
  "metadata": {
    "researchQuery": "emerging industry trends benefiting from simulation",
    "conductedAt": "2025-08-19T06:49:41.755Z",
    "method": "ai-analysis"
  },
  "createdAt": "2025-08-19T06:49:41.755Z",
  "updatedAt": "2025-08-19T06:49:41.755Z"
}