{
  "id": "44b1e1b2-0bc2-41fb-8a17-45ae7469a7b8",
  "sessionId": "s_njlk7hja5y9",
  "timestamp": "2025-08-18T05:24:26.816Z",
  "source": "diary",
  "topic": "Emerging technologies for storytelling in the energy sector 2023",
  "content": "Generated from lens processing: My working hypothesis is that current events and trending topics play a crucial role in shaping an effective story hook for marketing content. As a next step, I will research popular news stories, social media trends, and industry-specific updates to identify themes that resonate with the target audience. Additionally, I will explore competitor content strategies to gain insights into successful engagement techniques.",
  "tags": [
    "autopoietic",
    "lens-generated"
  ],
  "derivedTasks": [],
  "metadata": {
    "lensSessionId": "580601bd-7af2-408a-a8ca-9be96eb7984a",
    "trigger": "If I wanted to make marketing content today, what story hook would I use?",
    "generationTimestamp": "2025-08-18T05:24:26.816Z"
  },
  "createdAt": "2025-08-18T05:24:26.816Z",
  "updatedAt": "2025-08-18T05:24:26.816Z"
}