{
  "id": "4ee71dbc-08db-4455-9dc8-d30b5ec8e28a",
  "sessionId": "s_njlk7hja5y9",
  "timestamp": "2025-08-19T06:44:40.225Z",
  "source": "diary",
  "topic": "Common fears and misconceptions about solar energy adoption",
  "content": "Generated from lens processing: My working hypothesis is that the problem I'm avoiding likely stems from underlying fears or beliefs that make it feel overwhelming. The next step is to identify and articulate this specific problem and the emotions associated with it. I will take action by setting aside dedicated time to reflect on this issue, perhaps through journaling or discussing it with a trusted friend or counselor, to gain clarity and develop a plan to address it.",
  "tags": [
    "autopoietic",
    "lens-generated"
  ],
  "derivedTasks": [],
  "metadata": {
    "lensSessionId": "f6f4e723-4409-4edb-ab6f-4cdd966b843f",
    "trigger": "What problem am I avoiding thinking about?",
    "generationTimestamp": "2025-08-19T06:44:40.225Z"
  },
  "createdAt": "2025-08-19T06:44:40.225Z",
  "updatedAt": "2025-08-19T06:44:40.225Z"
}