{
  "id": "64c1caec-eb59-47d9-9949-52871223127f",
  "sessionId": "s_njlk7hja5y9",
  "timestamp": "2025-08-16T06:25:37.735Z",
  "source": "research",
  "topic": "Research: best platforms for sharing user-generated stories in marketing",
  "content": "**Research Summary: Best Platforms for Sharing User-Generated Stories in Marketing**\n\n1. **Key Findings or Insights:**\n\n   - **Social Media Dominance**: Platforms such as Instagram, Facebook, and TikTok are leading the charge in user-generated content (UGC) due to their vast user bases and engagement tools. Instagram's Stories and Reels, TikTok's viral challenges, and Facebook's groups and pages are particularly effective for storytelling.\n   \n   - **Emerging Platforms**: Newer platforms like Clubhouse and Discord are gaining traction, offering unique ways to engage audiences through audio and community-driven content. These platforms emphasize real-time interaction, which can enhance the authenticity of user-generated stories.\n   \n   - **Content Authenticity and Trust**: User-generated stories are perceived as more authentic than brand-created content. According to a study, 79% of people say user-generated content highly impacts their purchasing decisions.\n\n2. **Market Relevance (particularly for solar/AI/energy sectors):**\n   \n   - **Brand Advocacy**: In the solar and energy sectors, where trust and reliability are crucial, user-generated stories from satisfied customers can help build brand credibility and influence potential buyers.\n   \n   - **Educating Consumers**: For AI technologies, user stories can demystify complex products or services, making them more accessible to the average consumer. Platforms that facilitate detailed storytelling can help educate and engage audiences effectively.\n\n3. **Actionable Implications:**\n\n   - **Platform-Specific Strategies**: Brands should tailor their content strategies to the unique features and audience behaviors of each platform. For instance, leveraging Instagram's visual storytelling for solar installations or using TikTok to showcase quick, engaging AI demos.\n   \n   - **Community Building**: Invest in building communities on platforms like Discord where product enthusiasts can share experiences and solutions, fostering a supportive environment for user-generated content.\n   \n   - **Incentivizing Participation**: Encourage users to share their stories through contests, features, and rewards. This not only increases engagement but also generates a wealth of authentic content.\n\n4. **Questions for Further Investigation:**\n\n   - **What are the long-term impacts of user-generated content on brand loyalty and sales in the energy sector?**\n   \n   - **How can emerging platforms like Clubhouse and Discord be optimized for sharing more structured and impactful user-generated stories?**\n   \n   - **What role does AI play in curating and amplifying user-generated content for marketing purposes?**\n   \n",
  "tags": [
    "research",
    "autopoietic"
  ],
  "derivedTasks": [],
  "metadata": {
    "researchQuery": "best platforms for sharing user-generated stories in marketing",
    "conductedAt": "2025-08-16T06:25:37.735Z",
    "method": "ai-analysis"
  },
  "createdAt": "2025-08-16T06:25:37.735Z",
  "updatedAt": "2025-08-16T06:25:37.735Z"
}