{
  "id": "78ad056e-0c49-4186-b58d-972c5a53c517",
  "sessionId": "s_njlk7hja5y9",
  "timestamp": "2025-08-17T16:58:10.085Z",
  "source": "research",
  "topic": "Research: critical variables for agent-based modeling in urban planning",
  "content": "### Research Summary: Critical Variables for Agent-Based Modeling in Urban Planning\n\n#### Key Findings or Insights\n\nAgent-based modeling (ABM) is increasingly utilized in urban planning to simulate the interactions of agents (individuals, organizations, vehicles, etc.) within urban environments. Key variables critical to the efficacy of ABM in urban planning include:\n\n1. **Demographic Variables**: Age, income levels, and household composition are crucial for simulating residential mobility and market dynamics.\n   \n2. **Behavioral Factors**: Preferences, decision-making processes, and adaptability significantly affect traffic patterns, public transport usage, and residential choices.\n   \n3. **Spatial Variables**: Land use, geographic distribution of amenities, and infrastructure are fundamental for determining accessibility and urban sprawl.\n   \n4. **Environmental Factors**: Air quality, green space, and energy consumption are vital for assessing sustainability and resilience.\n\n5. **Policy and Governance**: Zoning laws, taxation policies, and governance structures impact urban development and must be accurately modeled.\n\n#### Market Relevance\n\nIn the context of the solar, AI, and energy sectors, ABM can provide valuable insights for optimizing the integration of renewable energy sources in urban settings. For instance, understanding demographic and behavioral factors can aid in predicting the adoption rate of solar technology among different urban populations. Spatial variables can help determine the optimal placement of solar panels or charging stations for electric vehicles. Additionally, policy variables can simulate the impact of incentives or regulations on energy consumption patterns.\n\n#### Actionable Implications\n\n1. **Data Collection and Integration**: Urban planners and policymakers should prioritize the collection of high-quality, granular data on the identified critical variables to enhance the accuracy of ABM simulations.\n   \n2. **Stakeholder Collaboration**: Engaging stakeholders from the solar and energy sectors can lead to better-aligned strategies that capitalize on the insights from ABM.\n\n3. **Scenario Analysis**: Use ABM to simulate various policy scenarios to evaluate potential impacts on urban development and energy consumption, aiding in more informed decision-making.\n\n4. **Sustainability Focus**: Incorporate environmental variables into ABM frameworks to ensure urban planning aligns with sustainability goals, especially in energy consumption and renewable integration.\n\n#### Questions for Further Investigation\n\n1. How can machine learning algorithms be integrated with ABM to enhance predictive accuracy in urban planning scenarios?\n   \n2. What are the limitations of current ABM frameworks in capturing the complexity of human behavior and decision-making in urban environments?\n\n3. How can AB",
  "tags": [
    "research",
    "autopoietic"
  ],
  "derivedTasks": [],
  "metadata": {
    "researchQuery": "critical variables for agent-based modeling in urban planning",
    "conductedAt": "2025-08-17T16:58:10.085Z",
    "method": "ai-analysis"
  },
  "createdAt": "2025-08-17T16:58:10.085Z",
  "updatedAt": "2025-08-17T16:58:10.085Z"
}