{
  "id": "8bfb8664-4096-472b-a9f2-2496014ac26e",
  "sessionId": "s_njlk7hja5y9",
  "timestamp": "2025-08-16T06:30:50.981Z",
  "source": "research",
  "topic": "Research: cultural influences on cognitive biases",
  "content": "### Key Findings or Insights\n\nCognitive biases, which are systematic patterns of deviation from norm or rationality in judgment, are significantly influenced by cultural contexts. Studies indicate that cultural dimensions such as individualism vs. collectivism, power distance, and uncertainty avoidance shape how cognitive biases manifest. For instance, individualistic cultures might display stronger self-serving biases, whereas collectivist cultures are more prone to biases that favor group harmony. Additionally, cultural norms influence susceptibility to biases like confirmation bias and anchoring. For example, in cultures with high power distance, individuals might be more inclined to conform to authority figures, thus affecting their critical thinking and decision-making processes.\n\n### Market Relevance\n\nIn sectors like solar, AI, and energy, understanding cultural influences on cognitive biases can be crucial. For AI, biases can affect algorithm design and data interpretation, leading to skewed outcomes if cultural contexts are not considered. In the solar and energy sectors, cultural biases can impact consumer behavior, policy formation, and the adoption of new technologies. Recognizing these biases can aid companies in tailoring marketing strategies and communication to better resonate with diverse cultural groups, thus enhancing market penetration and user engagement.\n\n### Actionable Implications\n\n1. **AI Development**: Incorporate cultural context into AI models to reduce bias and improve accuracy. This involves training AI systems on culturally diverse datasets and designing algorithms that account for cultural variability in decision-making.\n\n2. **Marketing Strategies**: For solar and energy products, develop culturally sensitive marketing campaigns that address specific biases prevalent in target markets. This could involve customized messaging that aligns with cultural values and decision-making processes.\n\n3. **Policy Design**: Policymakers should consider cultural biases when designing regulations and incentives in the energy sector. Culturally informed policies can lead to higher acceptance and effectiveness.\n\n### Questions for Further Investigation\n\n1. How do specific cultural dimensions (e.g., uncertainty avoidance) quantitatively affect the prevalence of certain cognitive biases?\n2. What are effective methodologies for integrating cultural context into AI systems to minimize bias?\n3. How can companies in the solar and energy sectors systematically identify and address cultural biases in their consumer base?\n4. What are the long-term impacts of culturally influenced cognitive biases on global energy consumption patterns and sustainability initiatives?\n\nUnderstanding the intersection of culture and cognitive biases is essential for creating more inclusive, effective technologies and policies in an increasingly globalized market. Further research in this area can lead to more equitable and efficient outcomes across various sectors.",
  "tags": [
    "research",
    "autopoietic"
  ],
  "derivedTasks": [],
  "metadata": {
    "researchQuery": "cultural influences on cognitive biases",
    "conductedAt": "2025-08-16T06:30:50.981Z",
    "method": "ai-analysis"
  },
  "createdAt": "2025-08-16T06:30:50.981Z",
  "updatedAt": "2025-08-16T06:30:50.981Z"
}