{
  "id": "9324e0de-bba4-4a69-86c5-8eda1c4105b7",
  "sessionId": "s_njlk7hja5y9",
  "timestamp": "2025-08-16T06:30:51.022Z",
  "source": "diary",
  "topic": "Cultural factors influencing solar energy adoption rates",
  "content": "Generated from lens processing: My working hypothesis is that my current assumptions might be influenced by cognitive biases or incomplete information. As a next step, I will actively seek out diverse perspectives and feedback from others to identify any blind spots in my thinking. Additionally, I will make it a regular practice to reflect on my assumptions and question their validity, potentially incorporating tools like assumption mapping or bias checklists to enhance this process.",
  "tags": [
    "autopoietic",
    "lens-generated"
  ],
  "derivedTasks": [],
  "metadata": {
    "lensSessionId": "441a1cfd-d20c-4b3a-87be-b7b85c90866c",
    "trigger": "What assumption am I making that might be wrong?",
    "generationTimestamp": "2025-08-16T06:30:51.022Z"
  },
  "createdAt": "2025-08-16T06:30:51.022Z",
  "updatedAt": "2025-08-16T06:30:51.022Z"
}