{
  "id": "a0680c07-6dc3-45e5-821b-36d7830e3583",
  "sessionId": "s_njlk7hja5y9",
  "timestamp": "2025-08-16T06:26:31.008Z",
  "source": "research",
  "topic": "Research: tools for visualizing connections between unrelated events",
  "content": "**Research Summary: Tools for Visualizing Connections Between Unrelated Events**\n\n1. **Key Findings or Insights:**\n   - Recent advancements in AI and data visualization have led to the development of sophisticated tools that can identify and visually present connections between seemingly unrelated events. These tools leverage machine learning algorithms, graph databases, and natural language processing to analyze vast datasets and uncover hidden patterns.\n   - Notable tools include Gephi, Neo4j, and IBM's Watson Discovery, which offer robust capabilities in mapping complex relationships. These platforms use graph theory to visualize connections, providing intuitive interfaces for users to explore and interpret data.\n   - Visualization techniques such as node-link diagrams, heat maps, and timelines are frequently used to represent the relationships and temporal aspects of the data. These methods help users to understand the context and significance of the connections more easily.\n\n2. **Market Relevance (Especially for Solar/AI/Energy Sectors):**\n   - In the energy sector, particularly solar, identifying connections between unrelated events can assist in optimizing grid management, predicting equipment failures, and enhancing supply chain logistics. For instance, correlating weather patterns with energy consumption and equipment performance can inform better operational strategies.\n   - AI-driven visualization tools can aid in anomaly detection within large datasets, crucial for cybersecurity in energy infrastructure. Understanding and visualizing these connections can preemptively address potential threats.\n   - These tools are also pivotal in strategic planning and decision-making, allowing businesses to foresee market trends and regulatory impacts, thereby maintaining a competitive edge.\n\n3. **Actionable Implications:**\n   - Organizations should invest in training their workforce to proficiently use these visualization tools, ensuring they can effectively interpret and act on the data insights provided.\n   - Companies in the solar and energy sectors should integrate these tools into their data analysis frameworks to enhance operational efficiency and strategic planning.\n   - There is a potential for developing customized visualization solutions tailored to specific industry needs, which could provide a competitive advantage in the marketplace.\n\n4. **Questions for Further Investigation:**\n   - How can these visualization tools be made more accessible and user-friendly for non-technical stakeholders in the industry?\n   - What are the limitations of current visualization techniques in accurately representing complex data relationships, and how can they be overcome?\n   - How can real-time data integration be improved in these tools to provide more timely insights and predictions?\n   - What specific case studies demonstrate the successful application of these tools in the solar and energy sectors, and what lessons can be learned from them",
  "tags": [
    "research",
    "autopoietic"
  ],
  "derivedTasks": [],
  "metadata": {
    "researchQuery": "tools for visualizing connections between unrelated events",
    "conductedAt": "2025-08-16T06:26:31.008Z",
    "method": "ai-analysis"
  },
  "createdAt": "2025-08-16T06:26:31.008Z",
  "updatedAt": "2025-08-16T06:26:31.008Z"
}