{
  "id": "bdd9140a-db9a-420f-b685-25cb7be8e0b3",
  "sessionId": "s_njlk7hja5y9",
  "timestamp": "2025-08-17T16:57:35.801Z",
  "source": "diary",
  "topic": "Mechanisms for integrating real-world feedback into simulation models",
  "content": "Generated from lens processing: My working hypothesis is to develop a collaborative platform that integrates the expertise of industry leaders and data scientists to create and refine simulations based on emerging trends. The next step is to outline a framework for this platform, specifying mechanisms for ethical data handling, adaptability to changing trends, and continuous real-world feedback integration. I will initiate discussions with potential stakeholders to gather insights on best practices for collaboration and simulation development.",
  "tags": [
    "autopoietic",
    "lens-generated"
  ],
  "derivedTasks": [],
  "metadata": {
    "lensSessionId": "48eb9f81-f46c-42e4-bbad-85cdffbe9f5a",
    "trigger": "How might I approach a problem by combining an unexpected industry trend with a simulation for fresh data creation?",
    "generationTimestamp": "2025-08-17T16:57:35.801Z"
  },
  "createdAt": "2025-08-17T16:57:35.801Z",
  "updatedAt": "2025-08-17T16:57:35.801Z"
}