{
  "id": "caf11150-5216-41d1-99bb-056b5c2e64ac",
  "sessionId": "s_njlk7hja5y9",
  "timestamp": "2025-08-16T06:38:09.154Z",
  "source": "research",
  "topic": "Research: iterative design methodologies in engineering",
  "content": "**Research Summary: Iterative Design Methodologies in Engineering**\n\n1. **Key Findings or Insights:**\n   Iterative design methodologies, such as Agile, Scrum, and Design Thinking, are increasingly being adopted in engineering disciplines to enhance innovation, flexibility, and efficiency. These methodologies emphasize cyclical processes where prototypes are continuously tested and refined based on feedback. Key insights include improved product quality, accelerated time-to-market, and increased stakeholder satisfaction. Iterative approaches foster a collaborative environment, encouraging cross-disciplinary teams to engage in continuous learning and adaptation. The iterative cycle of prototyping, testing, and refining is particularly beneficial in rapidly evolving fields, allowing engineers to respond effectively to new data and technological advancements.\n\n2. **Market Relevance:**\n   In sectors like solar energy, artificial intelligence (AI), and energy, iterative design methodologies hold significant market relevance. For solar energy, these methodologies enable rapid development of more efficient photovoltaic cells and integration systems by allowing for quick iterations based on testing results and environmental data. In AI, iterative methods are crucial for training models and refining algorithms through successive cycles of feedback and improvement. The energy sector, facing constant pressure to innovate sustainably, benefits from iterative design by accelerating the development of smart grids and renewable energy technologies, ensuring they meet evolving regulatory standards and consumer demands.\n\n3. **Actionable Implications:**\n   Organizations in the solar, AI, and energy sectors should integrate iterative design methodologies to remain competitive. For solar companies, this could mean adopting Agile frameworks to streamline the development of solar panels or battery storage systems. AI firms can enhance their model training processes by employing Scrum techniques to manage complex projects and improve algorithm accuracy. Energy companies might implement Design Thinking to explore user-centric solutions for renewable technologies, ensuring they align with customer needs and environmental goals. Training engineers in these methodologies can further enhance their strategic capabilities and improve project outcomes.\n\n4. **Questions for Further Investigation:**\n   - How can iterative design methodologies be adapted to overcome the specific challenges of high-stakes engineering projects, such as those in aerospace or nuclear energy?\n   - What are the potential drawbacks of iterative design, such as increased costs or resource allocation issues, and how can they be mitigated?\n   - How do cultural differences impact the adoption and effectiveness of iterative design methodologies in global engineering teams?\n   - What role do emerging technologies, like digital twins and AI-driven simulations, play in enhancing iterative design processes?\n\nThis research highlights the transformative potential of iterative design methodologies across various engineering sectors, offering pathways to increased innovation",
  "tags": [
    "research",
    "autopoietic"
  ],
  "derivedTasks": [],
  "metadata": {
    "researchQuery": "iterative design methodologies in engineering",
    "conductedAt": "2025-08-16T06:38:09.154Z",
    "method": "ai-analysis"
  },
  "createdAt": "2025-08-16T06:38:09.154Z",
  "updatedAt": "2025-08-16T06:38:09.154Z"
}